claude_commit/__init__.py
claude_commit/config.py
claude_commit/main.py
claude_commit-0.4.0.dist-info/licenses/LICENSE
claude_commit-0.4.0.dist-info/METADATA
claude_commit-0.4.0.dist-info/WHEEL
claude_commit-0.4.0.dist-info/entry_points.txt
claude_commit-0.4.0.dist-info/top_level.txt
claude_commit-0.4.0.dist-info/RECORD
